{"'Til Tuesday": [{"Voices Carry": {"YouTube": "https://www.youtube.com/watch?v=9pv1UVA1M0Y", "Spotify": "https://open.spotify.com/track/04pLdXwdbFUSezL2Gtjp5r"}}, {"Coming Up Close": {"YouTube": "https://www.youtube.com/watch?v=wtOgwFzhlyw", "Spotify": "https://open.spotify.com/track/5jGu0X5t3jTS40qDGqJ0Kv"}}, {"What About Love": {"YouTube": "https://www.youtube.com/watch?v=DZ48dMnqAy4", "Spotify": "https://open.spotify.com/track/03YERsfj67SCf84wzy7w1a"}}, {"Voices Carry - Single Mix": {"YouTube": "https://www.youtube.com/watch?v=aC2iNzu2OUU", "Spotify": "https://open.spotify.com/track/0fUrMeeCrjdNfbJNxjrOQN"}}, {"Love in a Vacuum": {"YouTube": "https://www.youtube.com/watch?v=WA0DtS25Wko", "Spotify": "https://open.spotify.com/track/3YNHkaT6U8U6IhopKHJvSf"}}], "*NSYNC": [{"Bye Bye Bye": {"YouTube": "https://www.youtube.com/watch?v=Eo-KmOd3i7s", "Spotify": "https://open.spotify.com/track/4r8lRYnoOGdEi6YyI5OC1o", "Apple Music": "https://geo.music.apple.com/album/id303171298?i=303171368&at=10l3Sh"}}, {"It's Gonna Be Me": {"YouTube": "https://www.youtube.com/watch?v=GQMlWwIXg3M", "Spotify": "https://open.spotify.com/track/1zDtC3p77g97HGRH3Xl1ri"}}, {"Merry Christmas, Happy Holidays": {"YouTube": "https://www.youtube.com/watch?v=wKj92352UAE", "Spotify": "https://open.spotify.com/track/6pXqCeH1mEU0VNlfU3plop", "Apple Music": "https://geo.music.apple.com/album/id1587240105?i=1587240124&at=10l3Sh"}}, {"This I Promise You": {"YouTube": "https://www.youtube.com/watch?v=6thmPrTxBtI", "Spotify": "https://open.spotify.com/track/2Dp2LRrY71XIfLe3co2Qnh"}}, {"Pop": {"YouTube": "https://www.youtube.com/watch?v=TWZKw_MgUPI", "Spotify": "https://open.spotify.com/track/0yRZqco2Jy8z6KAYlI6qcZ"}}], "+44": [{"When Your Heart Stops Beating": {"YouTube": "https://www.youtube.com/watch?v=2nWv2Hz_GXs", "Spotify": "https://open.spotify.com/track/5z7S8ITmKjMG9BztxgCf2s"}}, {"Lycanthrope": {"YouTube": "https://www.youtube.com/watch?v=wb-lgzDOsmo", "Spotify": "https://open.spotify.com/track/1g5CHtsDQl7KVWaUiAwat0"}}, {"Make You Smile": {"YouTube": "https://www.youtube.com/watch?v=Pun6OUeed-E", "Spotify": "https://open.spotify.com/track/5SXwcyArbvGKD4fAGHZ827"}}, {"155": {"YouTube": "https://www.youtube.com/watch?v=BG8fpwDlg34", "Spotify": "https://open.spotify.com/track/21DbQJZYawekrU056oFOND"}}, {"Baby Come On": {"YouTube": "https://www.youtube.com/watch?v=kbMRzqfkvms", "Spotify": "https://open.spotify.com/track/1BFCdZZgclq6WZJqDIPrwb"}}], "...And You Will Know Us by the Trail of Dead": [{"Another Morning Stoner": {"YouTube": "https://www.youtube.com/watch?v=kNf54L5uFZI", "Spotify": "https://open.spotify.com/track/05Jmd0J5HjkvbGKld9ChuA"}}, {"It Was There That I Saw You": {"YouTube": "https://www.youtube.com/watch?v=EK8gS9xTNz0", "Spotify": "https://open.spotify.com/track/3CIkPv8OOw5b81Dl6ujYpn"}}, {"How Near How Far": {"YouTube": "https://www.youtube.com/watch?v=ZJuGL-GWd-s", "Spotify": "https://open.spotify.com/track/1aklIImvCquLWbkOeGteRe"}}, {"Will You Smile Again?": {"YouTube": "https://www.youtube.com/watch?v=yeWiSOZItrE", "Spotify": "https://open.spotify.com/track/06L6ldA3rAsUrNWY4Q3vtu"}}, {"Baudelaire": {"YouTube": "https://www.youtube.com/watch?v=UWLMThnRJUQ", "Spotify": "https://open.spotify.com/track/2yiSdUGF2mJ0V39J1xZeb1"}}], ".38 Special": [{"Hold on Loosely": {"YouTube": "https://www.youtube.com/watch?v=g3nn6WfFQ7o", "Spotify": "https://open.spotify.com/track/6i9dZZQWNB06HKsQYKTiPF"}}, {"Caught Up in You": {"YouTube": "https://www.youtube.com/watch?v=zg21Rkew874", "Spotify": "https://open.spotify.com/track/0gOJikhgi0uMeH9JVD1zZs"}}, {"Rockin' Into the Night": {"YouTube": "https://www.youtube.com/watch?v=1722VFxD-qI", "Spotify": "https://open.spotify.com/track/1dCgVyxqZtyA0ah9HfxnDH"}}, {"Second Chance": {"YouTube": "https://www.youtube.com/watch?v=cRkaPdfjzEk", "Spotify": "https://open.spotify.com/track/0RAn8LOs5QVMLy2xH30bUj"}}, {"If I'd Been the One": {"YouTube": "https://www.youtube.com/watch?v=Q296T0L1IxU", "Spotify": "https://open.spotify.com/track/070lqiDS67dH5cqMiF32em"}}], "070 Shake": [{"Guilty Conscience": {"YouTube": "https://www.youtube.com/watch?v=X0t8zeEiqEY", "Spotify": "https://open.spotify.com/track/0KUTMPHXs64geBuZ0SUwN7", "Apple Music": "https://geo.music.apple.com/album/id1492318636?i=1492318640&at=10l3Sh"}}, {"Guilty Conscience - Tame Impala Remix": {"YouTube": "https://www.youtube.com/watch?v=4Nsq7ft9bjs", "Spotify": "https://open.spotify.com/track/5i5fCpsnqDJ9AfeObgd0gW"}}, {"Morrow": {"YouTube": "https://www.youtube.com/watch?v=JTEHO1W7Z2k", "Spotify": "https://open.spotify.com/track/6ibG3YAgbseFGSrj0gkcyl"}}, {"Under the Moon": {"YouTube": "https://www.youtube.com/watch?v=QdSLYNppSPw", "Spotify": "https://open.spotify.com/track/3RDgzyHD6uMNdCVnQIkD32"}}, {"Skin and Bones": {"YouTube": "https://www.youtube.com/watch?v=qEfYSU689mw", "Spotify": "https://open.spotify.com/track/2ZXLFYt9anzdwDOPpGJnui", "Apple Music": "https://geo.music.apple.com/album/id1622288641?i=1622289307&at=10l3Sh"}}]}